peppy_sage-0.1.16.dist-info/METADATA
peppy_sage-0.1.16.dist-info/WHEEL
peppy_sage/__init__.py
peppy_sage/_peppy_sage.pyd
peppy_sage/core.py
peppy_sage/indexing.py
peppy_sage/scoring.py
peppy_sage-0.1.16.dist-info/RECORD
