Metadata-Version: 2.4
Name: peppy_sage
Version: 0.1.16
Classifier: Programming Language :: Python :: 3
Classifier: Programming Language :: Rust
Classifier: Operating System :: OS Independent
Summary: Hybrid Rust/Python peptide scoring library
Author: Daniel Geiszler
License: MIT
Requires-Python: >=3.11
